KivyBannerMob/__init__.py
KivyBannerMob-1.2.1.dist-info/LICENSE
KivyBannerMob-1.2.1.dist-info/METADATA
KivyBannerMob-1.2.1.dist-info/WHEEL
KivyBannerMob-1.2.1.dist-info/top_level.txt
KivyBannerMob-1.2.1.dist-info/RECORD
