Metadata-Version: 2.1
Name: KivyBannerMob
Version: 1.2.1
Summary: Put Admob banner ads in your Kivy application
Home-page: https://github.com/ziyaad30/KivyBannerMob
Author: ziyaad30
Author-email: xavier.baatjes@outlook.com
License: UNKNOWN
Project-URL: Bug Tracker, https://github.com/ziyaad30/KivyBannerMob/issues
Platform: UNKNOWN
Classifier: Programming Language :: Python :: 3
Classifier: License :: OSI Approved :: MIT License
Classifier: Operating System :: OS Independent
Requires-Python: >=3.8
